LICENSE
MANIFEST.in
README.rst
setup.cfg
setup.py
django_json_schema_validator.egg-info/PKG-INFO
django_json_schema_validator.egg-info/SOURCES.txt
django_json_schema_validator.egg-info/dependency_links.txt
django_json_schema_validator.egg-info/top_level.txt
validator/__init__.py
validator/admin.py
validator/apps.py
validator/middleware.py
validator/models.py
validator/tests.py
validator/utils.py
validator/views.py
validator/management/__init__.py
validator/management/commands/__init__.py
validator/management/commands/gen_docs.py
validator/migrations/__init__.py